magic_window/__init__.py
magic_window/__main__.py
magic_window/stubs/i3ipc/__init__.pyi
magic_window/stubs/i3ipc/__version__.pyi
magic_window/stubs/i3ipc/_private/__init__.pyi
magic_window/stubs/i3ipc/_private/pubsub.pyi
magic_window/stubs/i3ipc/_private/sync.pyi
magic_window/stubs/i3ipc/_private/types.pyi
magic_window/stubs/i3ipc/aio/__init__.pyi
magic_window/stubs/i3ipc/aio/connection.pyi
magic_window/stubs/i3ipc/con.pyi
magic_window/stubs/i3ipc/connection.pyi
magic_window/stubs/i3ipc/events.pyi
magic_window/stubs/i3ipc/model.pyi
magic_window/stubs/i3ipc/replies.pyi
magic_window-0.1.0.dist-info/entry_points.txt
magic_window-0.1.0.dist-info/WHEEL
magic_window-0.1.0.dist-info/METADATA
magic_window-0.1.0.dist-info/RECORD
