Metadata-Version: 2.1
Name: magic-window
Version: 0.1.0
Summary: 
Author: Sean Collings
Author-email: seanrcollings@gmail.com
Requires-Python: >=3.9,<4.0
Classifier: Programming Language :: Python :: 3
Classifier: Programming Language :: Python :: 3.10
Classifier: Programming Language :: Python :: 3.9
Requires-Dist: arc-cli (>=6.2.2,<7.0.0)
Requires-Dist: i3ipc (>=2.2.1,<3.0.0)
